LICENSE.txt
MANIFEST.in
README.md
setup.py
cbtop.egg-info/PKG-INFO
cbtop.egg-info/SOURCES.txt
cbtop.egg-info/dependency_links.txt
cbtop.egg-info/requires.txt
cbtop.egg-info/top_level.txt
lib/EC2.py
lib/__init__.py
lib/cli_interface.py
lib/crc32.py
lib/exception.py
lib/load_runner.py
lib/logger.py
lib/mc_ascii_client.py
lib/mc_bin_client.py
lib/mc_bin_server.py
lib/memcacheConstants.py
lib/results_helper.py
lib/tap.py
lib/testconstants.py
lib/testrunner_common.py
lib/xunit.py
lib/bson/__init__.py
lib/bson/binary.py
lib/bson/code.py
lib/bson/dbref.py
lib/bson/errors.py
lib/bson/json_util.py
lib/bson/max_key.py
lib/bson/min_key.py
lib/bson/objectid.py
lib/bson/son.py
lib/bson/timestamp.py
lib/bson/tz_util.py
lib/builds/BeautifulSoup.py
lib/builds/__init__.py
lib/builds/build_query.py
lib/cbkarma/__init__.py
lib/cbkarma/rest_client.py
lib/couchbase/__init__.py
lib/couchbase/cluster.py
lib/couchbase/document.py
lib/couchbase/documentgenerator.py
lib/couchbase/stats_tools.py
lib/couchbase/view_helper.py
lib/couchdb/__init__.py
lib/couchdb/client.py
lib/couchdb/design.py
lib/couchdb/http.py
lib/couchdb/json.py
lib/couchdb/mapping.py
lib/couchdb/multipart.py
lib/couchdb/view.py
lib/membase/__init__.py
lib/membase/api/__init__.py
lib/membase/api/exception.py
lib/membase/api/mimeTypes.py
lib/membase/api/rest_client.py
lib/membase/api/tap.py
lib/membase/api/httplib2/__init__.py
lib/membase/api/httplib2/iri2uri.py
lib/membase/helper/__init__.py
lib/membase/helper/bucket_helper.py
lib/membase/helper/checkpoints.py
lib/membase/helper/cluster_helper.py
lib/membase/helper/failover_helper.py
lib/membase/helper/rebalance_helper.py
lib/membase/helper/spatial_helper.py
lib/membase/helper/stats.py
lib/membase/performance/__init__.py
lib/membase/performance/stats.py
lib/memcached/__init__.py
lib/memcached/helper/__init__.py
lib/memcached/helper/data_helper.py
lib/memcached/helper/kvstore.py
lib/memcached/helper/old_kvstore.py
lib/old_tasks/__init__.py
lib/old_tasks/task.py
lib/old_tasks/taskhelper.py
lib/old_tasks/taskmanager.py
lib/perf_engines/__init__.py
lib/perf_engines/cbsoda.py
lib/perf_engines/mcsoda.py
