Metadata-Version: 1.0
Name: cbtop
Version: 1.0.1
Summary: cbtop wrapper
Home-page: https://github.com/couchbaselabs/priority15
Author: couchbase
Author-email: admin@couchbase.com
License: Apache Software License
Keywords: couchbase,terminal,top,seriesly
Platform: UNKNOWN
Classifier: Intended Audience :: Developers
Classifier: Development Status :: 3 - Alpha
Classifier: Environment :: Console
Classifier: Operating System :: POSIX
Classifier: License :: OSI Approved :: Apache Software License
Classifier: Programming Language :: Python :: 2.6
Classifier: Programming Language :: Python :: 2.7
Classifier: Topic :: Software Development :: Libraries
Classifier: Topic :: Terminals
